{
  "tag": "div",
  "attributes": {
    "class": [
      "elementor-element",
      "elementor-element-1d0ba0fb",
      "elementor-grid-eael-col-3",
      "elementor-grid-mobile-eael-col-1",
      "elementor-grid-tablet-eael-col-2",
      "elementor-widget",
      "elementor-widget-eael-post-grid"
    ],
    "data-id": "1d0ba0fb",
    "data-element_type": "widget",
    "data-settings": "{\"eael_post_grid_columns\":\"eael-col-3\",\"eael_post_grid_columns_tablet\":\"eael-col-2\",\"eael_post_grid_columns_mobile\":\"eael-col-1\"}",
    "data-widget_type": "eael-post-grid.default"
  },
  "children": [
    {
      "tag": "div",
      "attributes": {
        "class": [
          "elementor-widget-container"
        ]
      },
      "children": [
        {
          "tag": "div",
          "attributes": {
            "id": [
              "eael-post-grid-1d0ba0fb"
            ],
            "class": [
              "eael-post-grid-container"
            ]
          },
          "children": [
            {
              "tag": "div",
              "attributes": {
                "class": [
                  "eael-post-appender",
                  "eael-post-appender-1d0ba0fb",
                  "eael-post-grid",
                  "eael-post-grid-style-two"
                ],
                "data-layout-mode": "masonry",
                "style": "position: relative; height: 363px;"
              },
              "children": [
                {
                  "tag": "article",
                  "attributes": {
                    "class": [
                      "eael-grid-post",
                      "eael-post-grid-column"
                    ],
                    "data-id": "224366",
                    "style": "position: absolute; left: 0%; top: 0px;"
                  },
                  "children": [
                    {
                      "tag": "div",
                      "attributes": {
                        "class": [
                          "eael-grid-post-holder"
                        ]
                      },
                      "children": [
                        {
                          "tag": "div",
                          "attributes": {
                            "class": [
                              "eael-grid-post-holder-inner"
                            ]
                          },
                          "children": [
                            {
                              "tag": "div",
                              "attributes": {
                                "class": [
                                  "eael-entry-media"
                                ]
                              },
                              "children": [
                                {
                                  "tag": "div",
                                  "attributes": {
                                    "class": [
                                      "eael-entry-overlay",
                                      "slide-up"
                                    ]
                                  },
                                  "children": [
                                    {
                                      "tag": "i",
                                      "attributes": {
                                        "class": [
                                          "fa-link",
                                          "fas"
                                        ],
                                        "aria-hidden": [
                                          "true"
                                        ]
                                      },
                                      "children": []
                                    },
                                    {
                                      "tag": "a",
                                      "attributes": {
                                        "href": "https://essential-addons.com/responsive-app-landing-pages/"
                                      },
                                      "children": []
                                    }
                                  ]
                                },
                                {
                                  "tag": "div",
                                  "attributes": {
                                    "class": [
                                      "",
                                      "eael-entry-thumbnail"
                                    ]
                                  },
                                  "children": [
                                    {
                                      "tag": "img",
                                      "attributes": {
                                        "loading": [
                                          "lazy"
                                        ],
                                        "decoding": [
                                          "async"
                                        ],
                                        "width": [
                                          "1280"
                                        ],
                                        "height": [
                                          "720"
                                        ],
                                        "src": "https://essential-addons.com/wp-content/uploads/2019/05/How-To-Build-Responsive-App-Landing-Pages-In-SECONDS-Elementor.png",
                                        "class": [
                                          "attachment-full",
                                          "size-full",
                                          "wp-image-254516"
                                        ],
                                        "alt": "Post Grid for Elementor 108",
                                        "srcset": "https://essential-addons.com/wp-content/uploads/2019/05/How-To-Build-Responsive-App-Landing-Pages-In-SECONDS-Elementor.png 1280w, https://essential-addons.com/wp-content/uploads/2019/05/How-To-Build-Responsive-App-Landing-Pages-In-SECONDS-Elementor-300x169.png 300w, https://essential-addons.com/wp-content/uploads/2019/05/How-To-Build-Responsive-App-Landing-Pages-In-SECONDS-Elementor-768x432.png 768w, https://essential-addons.com/wp-content/uploads/2019/05/How-To-Build-Responsive-App-Landing-Pages-In-SECONDS-Elementor-1024x576.png 1024w, https://essential-addons.com/wp-content/uploads/2019/05/How-To-Build-Responsive-App-Landing-Pages-In-SECONDS-Elementor-400x225.png 400w",
                                        "sizes": "(max-width: 1280px) 100vw, 1280px",
                                        "title": "Post Grid for Elementor 114"
                                      },
                                      "children": []
                                    }
                                  ]
                                }
                              ]
                            },
                            {
                              "tag": "div",
                              "attributes": {
                                "class": [
                                  "eael-entry-wrapper"
                                ]
                              },
                              "children": [
                                {
                                  "tag": "header",
                                  "attributes": {
                                    "class": [
                                      "eael-entry-header"
                                    ]
                                  },
                                  "children": [
                                    {
                                      "tag": "h2",
                                      "attributes": {
                                        "class": [
                                          "eael-entry-title"
                                        ]
                                      },
                                      "children": [
                                        {
                                          "tag": "a",
                                          "attributes": {
                                            "class": [
                                              "eael-grid-post-link"
                                            ],
                                            "href": "https://essential-addons.com/responsive-app-landing-pages/",
                                            "title": "How To Build Responsive App Landing Pages With Few Clicks"
                                          },
                                          "children": [
                                            {
                                              "text": "How To Build Responsive App Landing Pages With Few Clicks"
                                            }
                                          ]
                                        }
                                      ]
                                    }
                                  ]
                                },
                                {
                                  "tag": "div",
                                  "attributes": {
                                    "class": [
                                      "eael-entry-header-after",
                                      "style-two"
                                    ]
                                  },
                                  "children": []
                                }
                              ]
                            }
                          ]
                        }
                      ]
                    }
                  ]
                },
                {
                  "tag": "article",
                  "attributes": {
                    "class": [
                      "eael-grid-post",
                      "eael-post-grid-column"
                    ],
                    "data-id": "225740",
                    "style": "position: absolute; left: 33%; top: 0px;"
                  },
                  "children": [
                    {
                      "tag": "div",
                      "attributes": {
                        "class": [
                          "eael-grid-post-holder"
                        ]
                      },
                      "children": [
                        {
                          "tag": "div",
                          "attributes": {
                            "class": [
                              "eael-grid-post-holder-inner"
                            ]
                          },
                          "children": [
                            {
                              "tag": "div",
                              "attributes": {
                                "class": [
                                  "eael-entry-media"
                                ]
                              },
                              "children": [
                                {
                                  "tag": "div",
                                  "attributes": {
                                    "class": [
                                      "eael-entry-overlay",
                                      "slide-up"
                                    ]
                                  },
                                  "children": [
                                    {
                                      "tag": "i",
                                      "attributes": {
                                        "class": [
                                          "fa-link",
                                          "fas"
                                        ],
                                        "aria-hidden": [
                                          "true"
                                        ]
                                      },
                                      "children": []
                                    },
                                    {
                                      "tag": "a",
                                      "attributes": {
                                        "href": "https://essential-addons.com/elementor-templates/"
                                      },
                                      "children": []
                                    }
                                  ]
                                },
                                {
                                  "tag": "div",
                                  "attributes": {
                                    "class": [
                                      "",
                                      "eael-entry-thumbnail"
                                    ]
                                  },
                                  "children": [
                                    {
                                      "tag": "img",
                                      "attributes": {
                                        "loading": [
                                          "lazy"
                                        ],
                                        "decoding": [
                                          "async"
                                        ],
                                        "width": [
                                          "1280"
                                        ],
                                        "height": [
                                          "720"
                                        ],
                                        "src": "https://essential-addons.com/wp-content/uploads/2019/05/How-to-Import-and-Export-your-Templates-in-Elementor-1.png",
                                        "class": [
                                          "attachment-full",
                                          "size-full",
                                          "wp-image-254515"
                                        ],
                                        "alt": "Post Grid for Elementor 109",
                                        "srcset": "https://essential-addons.com/wp-content/uploads/2019/05/How-to-Import-and-Export-your-Templates-in-Elementor-1.png 1280w, https://essential-addons.com/wp-content/uploads/2019/05/How-to-Import-and-Export-your-Templates-in-Elementor-1-300x169.png 300w, https://essential-addons.com/wp-content/uploads/2019/05/How-to-Import-and-Export-your-Templates-in-Elementor-1-768x432.png 768w, https://essential-addons.com/wp-content/uploads/2019/05/How-to-Import-and-Export-your-Templates-in-Elementor-1-1024x576.png 1024w, https://essential-addons.com/wp-content/uploads/2019/05/How-to-Import-and-Export-your-Templates-in-Elementor-1-400x225.png 400w",
                                        "sizes": "(max-width: 1280px) 100vw, 1280px",
                                        "title": "Post Grid for Elementor 115"
                                      },
                                      "children": []
                                    }
                                  ]
                                }
                              ]
                            },
                            {
                              "tag": "div",
                              "attributes": {
                                "class": [
                                  "eael-entry-wrapper"
                                ]
                              },
                              "children": [
                                {
                                  "tag": "header",
                                  "attributes": {
                                    "class": [
                                      "eael-entry-header"
                                    ]
                                  },
                                  "children": [
                                    {
                                      "tag": "h2",
                                      "attributes": {
                                        "class": [
                                          "eael-entry-title"
                                        ]
                                      },
                                      "children": [
                                        {
                                          "tag": "a",
                                          "attributes": {
                                            "class": [
                                              "eael-grid-post-link"
                                            ],
                                            "href": "https://essential-addons.com/elementor-templates/",
                                            "title": "How to Import and Export your Templates in Elementor"
                                          },
                                          "children": [
                                            {
                                              "text": "How to Import and Export your Templates in Elementor"
                                            }
                                          ]
                                        }
                                      ]
                                    }
                                  ]
                                },
                                {
                                  "tag": "div",
                                  "attributes": {
                                    "class": [
                                      "eael-entry-header-after",
                                      "style-two"
                                    ]
                                  },
                                  "children": []
                                }
                              ]
                            }
                          ]
                        }
                      ]
                    }
                  ]
                },
                {
                  "tag": "article",
                  "attributes": {
                    "class": [
                      "eael-grid-post",
                      "eael-post-grid-column"
                    ],
                    "data-id": "225383",
                    "style": "position: absolute; left: 66%; top: 0px;"
                  },
                  "children": [
                    {
                      "tag": "div",
                      "attributes": {
                        "class": [
                          "eael-grid-post-holder"
                        ]
                      },
                      "children": [
                        {
                          "tag": "div",
                          "attributes": {
                            "class": [
                              "eael-grid-post-holder-inner"
                            ]
                          },
                          "children": [
                            {
                              "tag": "div",
                              "attributes": {
                                "class": [
                                  "eael-entry-media"
                                ]
                              },
                              "children": [
                                {
                                  "tag": "div",
                                  "attributes": {
                                    "class": [
                                      "eael-entry-overlay",
                                      "slide-up"
                                    ]
                                  },
                                  "children": [
                                    {
                                      "tag": "i",
                                      "attributes": {
                                        "class": [
                                          "fa-link",
                                          "fas"
                                        ],
                                        "aria-hidden": [
                                          "true"
                                        ]
                                      },
                                      "children": []
                                    },
                                    {
                                      "tag": "a",
                                      "attributes": {
                                        "href": "https://essential-addons.com/gravity-forms-elementor/"
                                      },
                                      "children": []
                                    }
                                  ]
                                },
                                {
                                  "tag": "div",
                                  "attributes": {
                                    "class": [
                                      "",
                                      "eael-entry-thumbnail"
                                    ]
                                  },
                                  "children": [
                                    {
                                      "tag": "img",
                                      "attributes": {
                                        "loading": [
                                          "lazy"
                                        ],
                                        "decoding": [
                                          "async"
                                        ],
                                        "width": [
                                          "1280"
                                        ],
                                        "height": [
                                          "720"
                                        ],
                                        "src": "https://essential-addons.com/wp-content/uploads/2019/05/How-to-use-Gravity-Forms-Interesting-use2.png",
                                        "class": [
                                          "attachment-full",
                                          "size-full",
                                          "wp-image-254513"
                                        ],
                                        "alt": "Post Grid for Elementor 110",
                                        "srcset": "https://essential-addons.com/wp-content/uploads/2019/05/How-to-use-Gravity-Forms-Interesting-use2.png 1280w, https://essential-addons.com/wp-content/uploads/2019/05/How-to-use-Gravity-Forms-Interesting-use2-300x169.png 300w, https://essential-addons.com/wp-content/uploads/2019/05/How-to-use-Gravity-Forms-Interesting-use2-768x432.png 768w, https://essential-addons.com/wp-content/uploads/2019/05/How-to-use-Gravity-Forms-Interesting-use2-1024x576.png 1024w, https://essential-addons.com/wp-content/uploads/2019/05/How-to-use-Gravity-Forms-Interesting-use2-400x225.png 400w",
                                        "sizes": "(max-width: 1280px) 100vw, 1280px",
                                        "title": "Post Grid for Elementor 116"
                                      },
                                      "children": []
                                    }
                                  ]
                                }
                              ]
                            },
                            {
                              "tag": "div",
                              "attributes": {
                                "class": [
                                  "eael-entry-wrapper"
                                ]
                              },
                              "children": [
                                {
                                  "tag": "header",
                                  "attributes": {
                                    "class": [
                                      "eael-entry-header"
                                    ]
                                  },
                                  "children": [
                                    {
                                      "tag": "h2",
                                      "attributes": {
                                        "class": [
                                          "eael-entry-title"
                                        ]
                                      },
                                      "children": [
                                        {
                                          "tag": "a",
                                          "attributes": {
                                            "class": [
                                              "eael-grid-post-link"
                                            ],
                                            "href": "https://essential-addons.com/gravity-forms-elementor/",
                                            "title": "Interesting Ways To Use Gravity Forms In Your WordPress Website With Elementor"
                                          },
                                          "children": [
                                            {
                                              "text": "Interesting Ways To Use Gravity Forms In Your WordPress Website With Elementor"
                                            }
                                          ]
                                        }
                                      ]
                                    }
                                  ]
                                },
                                {
                                  "tag": "div",
                                  "attributes": {
                                    "class": [
                                      "eael-entry-header-after",
                                      "style-two"
                                    ]
                                  },
                                  "children": []
                                }
                              ]
                            }
                          ]
                        }
                      ]
                    }
                  ]
                }
              ]
            },
            {
              "tag": "div",
              "attributes": {
                "class": [
                  "clearfix"
                ]
              },
              "children": []
            }
          ]
        },
        {
          "tag": "div",
          "attributes": {
            "class": [
              "eael-force-hide",
              "eael-load-more-button-wrap"
            ]
          },
          "children": [
            {
              "tag": "button",
              "attributes": {
                "class": [
                  "eael-load-more-button"
                ],
                "id": [
                  "eael-load-more-btn-1d0ba0fb"
                ],
                "data-widget-id": "1d0ba0fb",
                "data-widget": "1d0ba0fb",
                "data-page-id": "1345",
                "data-template": "{\"dir\":\"lite\",\"file_name\":\"default.php\",\"name\":\"Post-Grid\"}",
                "data-class": "Essential_Addons_Elementor\\Elements\\Post_Grid",
                "data-layout": "masonry",
                "data-page": "1",
                "data-args": "orderby=modified&order=asc&ignore_sticky_posts=1&post_status=publish&posts_per_page=3&offset=8&post_type=post&post__not_in%5B0%5D=221280&post__not_in%5B1%5D=223158",
                "data-max-page": "100"
              },
              "children": [
                {
                  "tag": "span",
                  "attributes": {
                    "class": [
                      "button__loader",
                      "eael-btn-loader"
                    ]
                  },
                  "children": []
                },
                {
                  "tag": "span",
                  "attributes": {
                    "class": [
                      "eael_load_more_text"
                    ]
                  },
                  "children": [
                    {
                      "text": "Load More"
                    }
                  ]
                }
              ]
            }
          ]
        }
      ]
    }
  ]
}